SanyTool/SYTools.py
SanyTool/__init__.py
SanyTool-1.1.1.dist-info/METADATA
SanyTool-1.1.1.dist-info/WHEEL
SanyTool-1.1.1.dist-info/top_level.txt
SanyTool-1.1.1.dist-info/RECORD
